MANIFEST.in
README.rst
setup.py
randomaya/__init__.py
randomaya/command_line.py
randomaya/randomaya.py
randomaya/test.py
randomaya.egg-info/PKG-INFO
randomaya.egg-info/SOURCES.txt
randomaya.egg-info/dependency_links.txt
randomaya.egg-info/entry_points.txt
randomaya.egg-info/not-zip-safe
randomaya.egg-info/top_level.txt
randomaya/data/en.pickthall.xml
randomaya/data/en.sahih.xml