Metadata-Version: 1.1
Name: randomaya
Version: 0.1.5
Summary: Random aya generator
Home-page: https://github.com/ansarb/randomaya
Author: Ansar Bedharudeen
Author-email: 1ns1rb@gmail.com
License: MIT
Keywords: Holy Quran Aya Islam Muslim
Platform: UNKNOWN
Classifier: Intended Audience :: Religion
Classifier: Topic :: Religion
Classifier: Programming Language :: Python :: 2.7
Classifier: Intended Audience :: Developers
